vt_police_tools
