Metadata-Version: 2.1
Name: vt-police-tools
Version: 2020.8.post3
Summary: Tools for cleaning Vermont police data
Home-page: https://github.com/brianmwaters/vt-police-tools/
Author: BTV CopWatch
Author-email: info@btvcopwatch.org
License: UNKNOWN
Project-URL: BTV CopWatch, https://www.btvcopwatch.org/
Project-URL: OpenOversight, https://www.openoversight.com/
Keywords: police vermont
Platform: UNKNOWN
Classifier: Development Status :: 5 - Production/Stable
Classifier: Environment :: Console
Classifier: Intended Audience :: Other Audience
Classifier: License :: CC0 1.0 Universal (CC0 1.0) Public Domain Dedication
Classifier: Natural Language :: English
Classifier: Operating System :: POSIX :: Linux
Classifier: Programming Language :: Python
Classifier: Programming Language :: Python :: 3
Classifier: Programming Language :: Python :: 3.7
Classifier: Programming Language :: Python :: Implementation :: CPython
Classifier: Topic :: Other/Nonlisted Topic
Requires-Python: ~=3.7
